ckanloader/__init__.py
ckanloader/loader.py
ckan_remote_dataloader-0.0.11.dist-info/LICENSE
ckan_remote_dataloader-0.0.11.dist-info/METADATA
ckan_remote_dataloader-0.0.11.dist-info/WHEEL
ckan_remote_dataloader-0.0.11.dist-info/dependency_links.txt
ckan_remote_dataloader-0.0.11.dist-info/entry_points.txt
ckan_remote_dataloader-0.0.11.dist-info/top_level.txt
ckan_remote_dataloader-0.0.11.dist-info/RECORD
